{
 "actions": [],
 "allow_rename": 1,
 "autoname": "field:hotel",
 "creation": "2025-01-13 11:43:10.065399",
 "doctype": "DocType",
 "editable_grid": 1,
 "engine": "InnoDB",
 "field_order": [
  "hotel",
  "commission"
 ],
 "fields": [
  {
   "fieldname": "hotel",
   "fieldtype": "Link",
   "in_list_view": 1,
   "label": "Hotel",
   "options": "Hotel",
   "reqd": 1,
   "unique": 1
  },
  {
   "fieldname": "commission",
   "fieldtype": "Currency",
   "in_list_view": 1,
   "label": "Commission",
   "non_negative": 1,
   "reqd": 1
  }
 ],
 "index_web_pages_for_search": 1,
 "istable": 1,
 "links": [],
 "modified": "2025-01-13 11:46:25.503859",
 "modified_by": "Administrator",
 "module": "Travels",
 "name": "Hotel Partnership",
 "naming_rule": "By fieldname",
 "owner": "Administrator",
 "permissions": [],
 "sort_field": "modified",
 "sort_order": "DESC",
 "states": []
}